pydestiny-0.1.0.dist-info/METADATA
pydestiny-0.1.0.dist-info/WHEEL
pydestiny.cp37-win_amd64.pyd
pydestiny-0.1.0.dist-info/RECORD
