Metadata-Version: 2.1
Name: pydestiny
Version: 0.1.0
Summary: A python wrapper for the rust crate destiny. A library for rolling dice and calculating dice distributions.
Author: Marc Chesebro <marc.chesebro@gmail.com>
Author-Email: Marc Chesebro <marc.chesebro@gmail.com>
License: MIT
